Workbook

Sheet Portada
A5: Checklist de Certificación IVA e IEPS (CERTIVA)
A6: RGCE 2026 · DOF 27/12/2025 · Decreto IMMEX vigente
B13: DATOS DEL PROYECTO
B14: Empresa:
B15: RFC:
B16: Rubro CERTIVA:
B17: Fecha de inicio:
B18: Responsable RB:
B19: Fecha de renovación:
B20: Vigencia:
B23: NAVEGACIÓN RÁPIDA — Haz clic en cada sección
B24: 📊 Dashboard | C24: ✅ Req. Generales | D24: 📋 Req. por Rubro | F24: ⚙️ Obligaciones | G24: ⚠️ Requerimiento
B25: HOJAS IMMEX (nuevas)
B26: 📦 IMMEX Obligaciones | D26: ❌ IMMEX Cancelación | F26: 🏭 IMMEX Activo Fijo

Sheet Dashboard
A2: DASHBOARD — Certificación IVA e IEPS (CERTIVA)
A3: · RGCE 2026 (DOF 27/12/2025) · Actualización automática
B7: 📋 TOTAL ÍTEMS | H7: ✅ CUMPLIDOS
B8: =110 -> 110 | H8: =COUNTIF(Req_Generales!B8:B32,"Cumplido")+COUNTIF(Req_Rubro!B8:B25,"Cumplido")+COUNTIF(IMMEX_Obligaciones!B8:B17,"Cumplido")+COUNTIF(IMMEX_Cancelacion!B9:B18,"Cumplido")+COUNTIF(IMMEX_ActivoFijo!B9:B15,"Cumplido")+COUNTIF(Obligaciones!B8:B19,"Cumplido")+COUNTIF(Requerimiento!B9:B25,"Cumplido")+COUNTIF(Cancelacion!B9:B30,"Cumplido") -> 0
B10: ⚠️ EN RIESGO | H10: ⏳ PENDIENTES
B11: =COUNTIF(Req_Generales!B8:B32,"En riesgo")+COUNTIF(Req_Rubro!B8:B25,"En riesgo")+COUNTIF(IMMEX_Obligaciones!B8:B17,"En riesgo")+COUNTIF(IMMEX_Cancelacion!B9:B18,"En riesgo")+COUNTIF(IMMEX_ActivoFijo!B9:B15,"En riesgo")+COUNTIF(Obligaciones!B8:B19,"En riesgo")+COUNTIF(Requerimiento!B9:B25,"En riesgo")+COUNTIF(Cancelacion!B9:B30,"En riesgo") -> 0 | H11: =COUNTIF(Req_Generales!B8:B32,"Pendiente")+COUNTIF(Req_Rubro!B8:B25,"Pendiente")+COUNTIF(IMMEX_Obligaciones!B8:B17,"Pendiente")+COUNTIF(IMMEX_Cancelacion!B9:B18,"Pendiente")+COUNTIF(IMMEX_ActivoFijo!B9:B15,"Pendiente")+COUNTIF(Obligaciones!B8:B19,"Pendiente")+COUNTIF(Requerimiento!B9:B25,"Pendiente")+COUNTIF(Cancelacion!B9:B30,"Pendiente") -> 110
B13: ➖ N/A | H13: 📊 % AVANCE
B14: =COUNTIF(Req_Generales!B8:B32,"N/A")+COUNTIF(Req_Rubro!B8:B25,"N/A")+COUNTIF(IMMEX_Obligaciones!B8:B17,"N/A")+COUNTIF(IMMEX_Cancelacion!B9:B18,"N/A")+COUNTIF(IMMEX_ActivoFijo!B9:B15,"N/A")+COUNTIF(Obligaciones!B8:B19,"N/A")+COUNTIF(Requerimiento!B9:B25,"N/A")+COUNTIF(Cancelacion!B9:B30,"N/A") -> 0 | H14: =IFERROR((COUNTIF(Req_Generales!B8:B32,"Cumplido")+COUNTIF(Req_Rubro!B8:B25,"Cumplido")+COUNTIF(IMMEX_Obligaciones!B8:B17,"Cumplido")+COUNTIF(IMMEX_Cancelacion!B9:B18,"Cumplido")+COUNTIF(IMMEX_ActivoFijo!B9:B15,"Cumplido")+COUNTIF(Obligaciones!B8:B19,"Cumplido")+COUNTIF(Requerimiento!B9:B25,"Cumplido")+COUNTIF(Cancelacion!B9:B30,"Cumplido"))/(110-(COUNTIF(Req_Generales!B8:B32,"N/A")+COUNTIF(Req_Rubro!B8:B25,"N/A")+COUNTIF(IMMEX_Obligaciones!B8:B17,"N/A")+COUNTIF(IMMEX_Cancelacion!B9:B18,"N/A")+COUNTIF(IMMEX_ActivoFijo!B9:B15,"N/A")+COUNTIF(Obligaciones!B8:B19,"N/A")+COUNTIF(Requerimiento!B9:B25,"N/A")+COUNTIF(Cancelacion!B9:B30,"N/A"))),0) -> 0
B18: AVANCE POR SECCIÓN
B20: Sección | G20: Total | H20: Cumplidos | I20: En riesgo | J20: Pendientes | K20: % Avance
B21: 1. Requisitos Generales | G21: 22 | H21: =COUNTIF(Req_Generales!B8:B32,"Cumplido") -> 0 | I21: =COUNTIF(Req_Generales!B8:B32,"En riesgo") -> 0 | J21: =COUNTIF(Req_Generales!B8:B32,"Pendiente") -> 22 | K21: =IFERROR(H21/(G21-COUNTIF(Req_Generales!B8:B32,"N/A")),0) -> 0
B22: 2. Requisitos por Rubro | G22: 16 | H22: =COUNTIF(Req_Rubro!B8:B25,"Cumplido") -> 0 | I22: =COUNTIF(Req_Rubro!B8:B25,"En riesgo") -> 0 | J22: =COUNTIF(Req_Rubro!B8:B25,"Pendiente") -> 16 | K22: =IFERROR(H22/(G22-COUNTIF(Req_Rubro!B8:B25,"N/A")),0) -> 0
B23: 3. Obligaciones Permanentes | G23: 11 | H23: =COUNTIF(Obligaciones!B8:B19,"Cumplido") -> 0 | I23: =COUNTIF(Obligaciones!B8:B19,"En riesgo") -> 0 | J23: =COUNTIF(Obligaciones!B8:B19,"Pendiente") -> 11 | K23: =IFERROR(H23/(G23-COUNTIF(Obligaciones!B8:B19,"N/A")),0) -> 0
B24: 4. Causas de Requerimiento | G24: 16 | H24: =COUNTIF(Requerimiento!B9:B25,"Cumplido") -> 0 | I24: =COUNTIF(Requerimiento!B9:B25,"En riesgo") -> 0 | J24: =COUNTIF(Requerimiento!B9:B25,"Pendiente") -> 16 | K24: =IFERROR(H25/(G25-COUNTIF(Requerimiento!B9:B25,"N/A")),0) -> 0
B25: 5. Causas de Cancelación | G25: 20 | H25: =COUNTIF(Cancelacion!B9:B30,"Cumplido") -> 0 | I25: =COUNTIF(Cancelacion!B9:B30,"En riesgo") -> 0 | J25: =COUNTIF(Cancelacion!B9:B30,"Pendiente") -> 20 | K25: =IFERROR(H26/(G26-COUNTIF(Cancelacion!B9:B30,"N/A")),0) -> 0
B26: IMMEX — Obligaciones del Programa | G26: 9 | H26: =COUNTIF(IMMEX_Obligaciones!B8:B17,"Cumplido") -> 0 | I26: =COUNTIF(IMMEX_Obligaciones!B8:B17,"En riesgo") -> 0 | J26: =COUNTIF(IMMEX_Obligaciones!B8:B17,"Pendiente") -> 9 | K26: =IFERROR(H27/(G27-COUNTIF(IMMEX_Obligaciones!B8:B17,"N/A")),0) -> 0
B27: IMMEX — Causales de Cancelación | G27: 10 | H27: =COUNTIF(IMMEX_Cancelacion!B9:B18,"Cumplido") -> 0 | I27: =COUNTIF(IMMEX_Cancelacion!B9:B18,"En riesgo") -> 0 | J27: =COUNTIF(IMMEX_Cancelacion!B9:B18,"Pendiente") -> 10 | K27: =IFERROR(H28/(G28-COUNTIF(IMMEX_Cancelacion!B9:B18,"N/A")),0) -> 0
B28: IMMEX — Activo Fijo | G28: 6 | H28: =COUNTIF(IMMEX_ActivoFijo!B9:B15,"Cumplido") -> 0 | I28: =COUNTIF(IMMEX_ActivoFijo!B9:B15,"En riesgo") -> 0 | J28: =COUNTIF(IMMEX_ActivoFijo!B9:B15,"Pendiente") -> 6 | K28: =IFERROR(H29/(G29-COUNTIF(IMMEX_ActivoFijo!B9:B15,"N/A")),0) -> 0
B29: Pendiente | D29: Cumplido | F29: En riesgo | H29: N/A
B31: Elaborado con base en RGCE DOF 27/12/2025 · Decreto IMMEX vigente

Sheet Req_Generales
A2: 1. REQUISITOS GENERALES — Regla 7.1.1
A3: Obtención y renovación del Registro en el Esquema de Certificación de Empresas · IVA e IEPS
A4: RGCE 2026 (DOF 27/12/2025) · Decreto IMMEX vigente
A6: # | B6: Estatus | C6: Obligación / Requisito / Causal | D6: Referencia normativa | E6: Documento / Evidencia de cumplimiento | F6: Responsable | G6: Fecha de cumplimiento
A7: 1.1 Requisitos fiscales y legales
A8: 1 | B8: Pendiente | C8: Personas morales constituidas conforme a la legislación mexicana | D8: Regla 7.1.1 fracc. I | E8: Acta constitutiva | F8: Cliente
A9: 2 | B9: Pendiente | C9: Estar al corriente en obligaciones fiscales y aduaneras; autorizar al SAT para hacer pública la opinión positiva (Regla 2.1.24 RMF) | D9: 7.1.1 fracc. II · CFF art. 32-D | E9: Opinión de cumplimiento positiva (SAT) | F9: Cliente
A10: 3 | B10: Pendiente | C10: Contar con certificados de sellos digitales vigentes y no ubicarse en supuestos del art. 17-H Bis CFF en los últimos 12 meses | D10: 7.1.1 fracc. V · CFF art. 17-H Bis | E10: Certificados CSD vigentes | F10: Cliente
A11: 4 | B11: Pendiente | C11: No estar en listados SAT: art. 69 CFF (exc. fracc. VI), art. 69-B cuarto párrafo, art. 69-B Bis noveno párrafo | D11: 7.1.1 fracc. IV · CFF arts. 69, 69-B, 69-B Bis | E11: Constancia de consulta en listados SAT | F11: Asesor
A12: 5 | B12: Pendiente | C12: No haberse emitido resolución de emisión de falsos comprobantes fiscales (art. 49 Bis CFF) | D12: 7.1.1 fracc. XXI · CFF art. 49 Bis | F12: Cliente
A13: 6 | B13: Pendiente | C13: Socios, accionistas, representante legal e integrantes de administración al corriente en obligaciones fiscales | D13: 7.1.1 fracc. XVI | E13: Opiniones positivas de socios/accionistas | F13: Cliente
A14: 7 | B14: Pendiente | C14: Socios/accionistas y administración no vinculados con empresa a quien se le canceló el registro (regla 7.2.4) | D14: 7.1.1 fracc. XVII · Regla 7.2.4 | F14: Cliente
A15: 8 | B15: Pendiente | C15: Ningún socio condenado por delitos que ameriten pena corporal | D15: 7.1.1 fracc. XVIII | E15: Manifestación bajo protesta de decir verdad | F15: Cliente
A16: 9 | B16: Pendiente | C16: Sin sanciones administrativas por importación o exportación de mercancías | D16: 7.1.1 fracc. XIX | E16: Manifestación bajo protesta de decir verdad | F16: Cliente
A17: 10 | B17: Pendiente | C17: El SAT no haya interpuesto querella, denuncia penal o declaratoria de perjuicio contra socios/administración en los últimos 3 años | D17: 7.1.1 fracc. XIII | F17: Cliente
A18: 1.2 Domicilios e infraestructura
A19: 11 | B19: Pendiente | C19: Tener registrados ante el SAT todos los domicilios vinculados al Programa IMMEX o actividades de comercio exterior | D19: 7.1.1 fracc. VI · CFF art. 27 | E19: Capturas de pantalla SAT — domicilios localizados | F19: Cliente
A20: 12 | B20: Pendiente | C20: Legal uso o goce del inmueble donde se realizan los procesos con vigencia forzosa mínima de 1 año y al menos 8 meses restantes a la solicitud | D20: 7.1.1 fracc. XII | E20: Contrato de arrendamiento / título de propiedad | F20: Cliente
A21: 13 | B21: Pendiente | C21: Permitir en todo momento el acceso de la AGACE para visitas de inspección inicial y supervisión de cumplimiento | D21: 7.1.1 fracc. IX | F21: Cliente
A22: 14 | B22: Pendiente | C22: No estar suspendido en el Padrón de Importadores, Padrón de Importadores de Sectores Específicos o Padrón de Exportadores Sectorial | D22: 7.1.1 fracc. VIII | E22: Constancia de padrón activo | F22: Cliente
A23: 1.3 Clientes, proveedores y contabilidad
A24: 15 | B24: Pendiente | C24: Clientes y proveedores en el extranjero con operaciones de comercio exterior en los últimos 12 meses | D24: 7.1.1 fracc. X | E24: Listado de clientes/proveedores extranjeros | F24: Cliente
A25: 16 | B25: Pendiente | C25: En su caso, proveedores de insumos en territorio nacional vinculados al proceso en los últimos 6 meses | D25: 7.1.1 fracc. XI | E25: Listado de proveedores nacionales + opiniones positivas | F25: Cliente
A26: 17 | B26: Pendiente | C26: Llevar control de inventarios conforme al art. 59 fracc. I Ley Aduanera y Anexo 24 Apartado C | D26: 7.1.1 fracc. XIV · LA art. 59 | E26: Comprobante de Anexo 24 (SCCCyG) | F26: Asesor
A27: 18 | B27: Pendiente | C27: Llevar contabilidad en medios electrónicos e ingresarla mensualmente al Portal SAT (CFF arts. 28 fracc. III y IV; RMF 2.8.1.5 y 2.8.1.6) | D27: 7.1.1 fracc. XV | F27: Cliente
A28: 19 | B28: Pendiente | C28: Contar con buzón tributario actualizado — estatus 'Validado' (CFF art. 17-K) | D28: 7.1.1 fracc. VII · CFF art. 17-K | F28: Cliente
A29: 20 | B29: Pendiente | C29: Haber realizado el pago de derechos art. 40 inciso m) LFD — $40,267.00 mediante e5cinco (Anexo 4 RMF 2026) | D29: 7.1.1 fracc. XX · LFD art. 40 | E29: Comprobante e5cinco ($40,267.00) | F29: Cliente
A30: 1.4 Personal e IMSS
A31: 21 | B31: Pendiente | C31: Personal registrado ante el IMSS para el proceso productivo/servicio; al corriente en cuotas obrero-patronales; retener y enterar ISR de trabajadores | D31: 7.1.1 fracc. III · ISR art. 27 | E31: Constancias IMSS/SUA último bimestre + declaración ISR retenciones | F31: Cliente
A32: 22 | B32: Pendiente | C32: En caso de subcontratación de servicios especializados, cumplir con art. 27 fracc. V tercer párrafo de la Ley del ISR | D32: 7.1.1 fracc. III · ISR art. 27 fracc. V | E32: Documentación de subcontratación especializada | F32: Cliente

Sheet Req_Rubro
A2: 2. REQUISITOS POR RUBRO — Reglas 7.1.2 y 7.1.3
A3: Rubro A · Rubro AA · Rubro AAA
A4: RGCE 2026 (DOF 27/12/2025) · Decreto IMMEX vigente
A6: # | B6: Estatus | C6: Obligación / Requisito / Causal | D6: Referencia normativa | E6: Documento / Evidencia de cumplimiento | F6: Responsable | G6: Fecha de cumplimiento
A7: Rubro A — Regla 7.1.2 (incluye todos los requisitos de la Regla 7.1.1)
A8: 1 | B8: Pendiente | C8: Presentar solicitud mediante ficha de trámite 61/LA (Anexo 2) | D8: 7.1.2 fracc. I | F8: Asesor
A9: 2 | B9: Pendiente | C9: Mínimo 10 trabajadores registrados ante el IMSS y pago total de cuotas obrero-patronales | D9: 7.1.2 fracc. II | F9: Cliente
A10: 3 | B10: Pendiente | C10: Acreditar inversión en territorio nacional | D10: 7.1.2 fracc. III | F10: Cliente
A11: 4 | B11: Pendiente | C11: Si anteriormente tuvo el registro o garantizó el interés fiscal, estar al corriente con obligaciones del Anexo 30 (SCCCyG) | D11: 7.1.2 fracc. IV · Anexo 30 | F11: Asesor
A12: 5 | B12: Pendiente | C12: Proveedores no incluidos en listados SAT arts. 49 Bis fracc. X o 69-B cuarto párrafo CFF | D12: 7.1.2 fracc. V | F12: Asesor
A13: 6 | B13: Pendiente | C13: Contar con Programa IMMEX vigente | D13: 7.1.2 Apt. A, fracc. I | F13: Cliente
A14: 7 | B14: Pendiente | C14: Infraestructura suficiente para realizar la operación del Programa IMMEX conforme a su modalidad | D14: 7.1.2 Apt. A, fracc. II | F14: Cliente
A15: 8 | B15: Pendiente | C15: Haber importado temporalmente y retornado en los últimos 12 meses: ≥60% del valor total de importaciones temporales de insumos | D15: 7.1.2 Apt. A, fracc. III | F15: Asesor
A16: 9 | B16: Pendiente | C16: Describir actividades del proceso productivo desde el arribo, almacenamiento, proceso y retorno de mercancías | D16: 7.1.2 Apt. A, fracc. IV | F16: Cliente
A17: 10 | B17: Pendiente | C17: Contrato de maquila, compraventa, orden de compra, servicios o pedidos en firme que acrediten continuidad del proyecto de exportación | D17: 7.1.2 Apt. A, fracc. V | F17: Cliente
A18: Rubro AA — Regla 7.1.3 (incluye todos los requisitos del Rubro A)
A19: 11 | B19: Pendiente | C19: ≥4 años operando bajo el régimen solicitado, O promedio >1,000 trabajadores en los últimos 12 meses, O maquinaria y equipo con valor >$50,000,000 pesos | D19: 7.1.3 fracc. I inciso a) | F19: Cliente
A20: 12 | B20: Pendiente | C20: Sin crédito fiscal notificado por el SAT en los últimos 12 meses (o garantizado conforme art. 141 CFF / pago a plazos sin exceder 12 meses) | D20: 7.1.3 fracc. I inciso b) | F20: Cliente
A21: 13 | B21: Pendiente | C21: Sin resolución de improcedencia de devolución IVA >20% del total autorizado y/o monto negado >$5,000,000 pesos en los últimos 6 meses | D21: 7.1.3 fracc. I inciso c) | F21: Asesor
A22: Rubro AAA — Regla 7.1.3 (incluye todos los requisitos del Rubro AA)
A23: 14 | B23: Pendiente | C23: ≥7 años operando bajo el régimen solicitado, O promedio >2,500 trabajadores en los últimos 12 meses, O maquinaria y equipo con valor >$100,000,000 pesos | D23: 7.1.3 fracc. II inciso a) | F23: Cliente
A24: 15 | B24: Pendiente | C24: Sin crédito fiscal notificado por el SAT en los últimos 24 meses (o garantizado conforme art. 141 CFF) | D24: 7.1.3 fracc. II inciso b) | F24: Cliente
A25: 16 | B25: Pendiente | C25: Sin resolución de improcedencia de devolución IVA >20% del total autorizado y/o monto negado >$5,000,000 pesos en los últimos 6 meses | D25: 7.1.3 fracc. II inciso c) | F25: Asesor

Sheet IMMEX_Obligaciones
A2: IMMEX — OBLIGACIONES DEL PROGRAMA (Arts. 24, 25 · Decreto IMMEX · Regla 4.3.1 RGCE)
A3: Obligaciones de operación y reportes periódicos durante la vigencia del Programa IMMEX
A4: Decreto IMMEX vigente · RGCE 2026 (DOF 27/12/2025)
A6: # | B6: Estatus | C6: Obligación / Causal / Verificación | D6: Fundamento legal | E6: Acción requerida / Documento | F6: Responsable | G6: Fecha de cumplimiento
A7: Obligaciones de operación — Art. 24 Decreto IMMEX
A8: 1 | B8: Pendiente | C8: Realizar anualmente ventas al exterior por valor superior a USD $500,000 o facturar exportaciones cuando menos por el 10% de su facturación total | D8: Art. 24 Fracc. I Decreto IMMEX | E8: Verificar cifras de exportación del ejercicio anterior | F8: Cliente
A9: 2 | B9: Pendiente | C9: Cumplir con lo establecido en el Programa que les fue autorizado | D9: Art. 24 Fracc. II Decreto IMMEX | E9: Revisar que las operaciones correspondan al objeto del programa autorizado | F9: Asesor
A10: 3 | B10: Pendiente | C10: Retornar las mercancías en los plazos autorizados: 18 meses (insumos, materias primas, envases, etiquetas); 2 años (contenedores y cajas de trailer); vigencia del programa (maquinaria, equipo, herramientas, moldes, refacciones, equipo administrativo); 6 meses (mercancías sujetas a transferencia virtual) | D10: Art. 24 Fracc. V Art. 4 Decreto IMMEX | E10: Verificar que todos los pedimentos temporales hayan sido retornados, transferidos o con cambio de régimen dentro del plazo | F10: Asesor
A11: 4 | B11: Pendiente | C11: Mantener las mercancías importadas temporalmente en el o los domicilios registrados en el Programa | D11: Art. 24 Fracc. VI Decreto IMMEX | E11: Adjuntar acuses de alta de domicilio y confirmar que no existe otro domicilio al que llegue mercancía IMMEX | F11: Cliente
A12: 5 | B12: Pendiente | C12: Solicitar a la SE el registro de cambios en datos manifestados en la solicitud: razón social, RFC, domicilio fiscal (con al menos 3 días hábiles de anticipación al traslado de mercancías) | D12: Art. 24 Fracc. VII Decreto IMMEX | E12: Indicar si la empresa ha tenido cambios. De ser así, adjuntar escritos enviados a la SE | F12: Cliente
A13: 6 | B13: Pendiente | C13: Notificar a la SE los cambios de socios, accionistas o representante legal | D13: Art. 24 Fracc. VIII Decreto IMMEX | E13: Indicar si ha habido cambios de socios, accionistas o representante legal desde 2018. De ser así, adjuntar el aviso correspondiente | F13: Cliente
A14: 7 | B14: Pendiente | C14: Llevar el control de inventarios en forma automatizada, conforme a las Reglas de Carácter General (Anexo 24) | D14: Art. 24 Fracc. IX Decreto IMMEX Regla 4.3.1 RGCE | E14: Adjuntar comprobante que acredite que se cuenta con el Anexo 24 y confirmar que se cuenta con la información del Apartado A | F14: Asesor
A15: Reportes periódicos — Arts. 25 y Regla 3.2.17
A16: 8 | B16: Pendiente | C16: Presentar reporte anual electrónico a la SE del total de ventas y exportaciones del ejercicio anterior, a más tardar el último día hábil de mayo | D16: Art. 25 Primer párrafo Decreto IMMEX | E16: Verificar que se haya presentado el reporte anual del ejercicio anterior | F16: Cliente
A17: 9 | B17: Pendiente | C17: Presentar información estadística al INEGI mensualmente (dentro de los primeros 20 días naturales del mes siguiente) o anualmente (dentro de los 30 días posteriores a la notificación del INEGI) | D17: Art. 25 Quinto párrafo Regla 3.2.17 Acuerdo SE | E17: Confirmar que se presenta la información al INEGI conforme al calendario establecido | F17: Cliente

Sheet IMMEX_Cancelacion
A2: IMMEX — CAUSALES DE CANCELACIÓN DEL PROGRAMA (Art. 27 · Decreto IMMEX)
A3: Situaciones que pueden derivar en la cancelación definitiva del Programa IMMEX
A4: Decreto IMMEX vigente · RGCE 2026 (DOF 27/12/2025)
A6: # | B6: Estatus | C6: Causal de cancelación | D6: Fundamento legal | E6: Acción requerida / Documento | F6: Responsable | G6: Fecha de cumplimiento
A7: Causales de cancelación del Programa IMMEX — Art. 27 Decreto IMMEX + Regla 3.2.9 Acuerdo SE
A8: ℹ️ La cancelación del Programa IMMEX también puede desencadenar la cancelación del registro CERTIVA (Regla 7.2.4 Apt. B fracc. I). Es crítico monitorear estas causales.
A9: 1 | B9: Pendiente | C9: Incumplimiento de alguna de las obligaciones previstas en el Decreto IMMEX | D9: Art. 27 Fracc. I Decreto IMMEX | E9: Verificar que todas las obligaciones del Art. 24 y 25 estén cumplidas | F9: Asesor
A10: 2 | B10: Pendiente | C10: Para efectos del Art. 27 Fracc. I, se considera plenamente acreditado el incumplimiento cuando el beneficiario haya retornado, transferido la mercancía o efectuado el cambio de régimen de importación temporal a definitiva, fuera del plazo previsto en las normas aplicables | D10: Regla 3.2.9 Acuerdo SE | E10: Confirmar que no se han retornado o transferido mercancías fuera del plazo autorizado | F10: Asesor
A11: 3 | B11: Pendiente | C11: No contar con documentación que ampare sus operaciones o no acreditar la legal estancia/tenencia de mercancías de procedencia extranjera, y el crédito fiscal determinado sea mayor a $400,000; o cuando el valor de las mercancías sin acreditar supere el 5% del valor total importado temporalmente en el semestre anterior | D11: Art. 27 Fracc. II Decreto IMMEX | E11: Confirmar que toda mercancía de procedencia extranjera cuenta con documentación aduanera que acredite su legal estancia | F11: Asesor
A12: 4 | B12: Pendiente | C12: No ser localizable en el domicilio fiscal o en los domicilios registrados en el Programa, o que dichos domicilios estén en supuesto de no localizados o inexistentes | D12: Art. 27 Fracc. III Decreto IMMEX | E12: Adjuntar capturas de pantalla del SAT que muestren los domicilios como localizados | F12: Cliente
A13: 5 | B13: Pendiente | C13: No encontrarse las mercancías importadas temporalmente en los domicilios registrados ante el SAT, hasta por un monto equivalente al establecido en el Art. 102 tercer párrafo del CFF | D13: Art. 27 Fracc. IV Decreto IMMEX | E13: Confirmar que las mercancías IMMEX se encuentran en los domicilios autorizados | F13: Asesor
A14: 6 | B14: Pendiente | C14: Que el SAT determine que las mercancías importadas temporalmente no ingresaron físicamente al país de destino o no se presentaron físicamente en la aduana de salida al extranjero, una vez tramitado el pedimento de exportación o retorno | D14: Art. 27 Fracc. V Decreto IMMEX | E14: Confirmar que las mercancías hayan ingresado físicamente al país destino y se presentaron ante aduana | F14: Cliente
A15: 7 | B15: Pendiente | C15: Presentar documentación falsa, alterada o con datos falsos; o que el nombre/domicilio del proveedor, destinatario o comprador en pedimentos o facturas sean falsos, inexistentes o no localizados | D15: Art. 27 Fracc. VI Decreto IMMEX | E15: Confirmar que no se ha presentado documentación falsa, alterada o con datos falsos | F15: Cliente
A16: 8 | B16: Pendiente | C16: Presentar aviso de cancelación en el RFC o no presentar la declaración anual de los impuestos federales por los que se encuentre obligada | D16: Art. 27 Fracc. VII Decreto IMMEX | E16: Confirmar que no se tenga aviso de cancelación en el RFC. Adjuntar comprobante de declaraciones anuales presentadas | F16: Cliente
A17: 9 | B17: Pendiente | C17: Que la autoridad determine que sus socios y/o accionistas se encuentran vinculados con alguna empresa a la que se le hubiera cancelado su Programa | D17: Art. 27 Fracc. VIII Decreto IMMEX | E17: Confirmar que los socios y accionistas no están vinculados con empresa a la que se haya cancelado su programa | F17: Cliente
A18: 10 | B18: Pendiente | C18: No acreditar que se realizó la entrega física de las mercancías importadas temporalmente derivado de operaciones de transferencias y/o avisos de submaquila | D18: Art. 27 Fracc. IX Decreto IMMEX | E18: Confirmar que se haya acreditado la entrega física de las mercancías en todas las operaciones de transferencia | F18: Asesor

Sheet IMMEX_ActivoFijo
A2: IMMEX — ACTIVO FIJO (Arts. 36-A, 146 LA · Art. 24 Decreto IMMEX · Anexo 24 RGCE)
A3: Obligaciones específicas para el control y legal estancia del activo fijo importado temporalmente
A4: Decreto IMMEX vigente · RGCE 2026 (DOF 27/12/2025)
A6: # | B6: Estatus | C6: Obligación / Causal / Verificación | D6: Fundamento legal | E6: Acción requerida / Documento | F6: Responsable | G6: Fecha de cumplimiento
A7: Definición y tipos de activo fijo importado temporalmente
A8: ℹ️ La importación temporal de activo fijo es por la vigencia del Programa IMMEX. Incluye: maquinaria, equipo, herramientas, instrumentos, moldes, refacciones, equipo de control ambiental, TI, laboratorio, calidad y equipo administrativo.
A9: 1 | B9: Pendiente | C9: Para mercancías susceptibles de identificación individual: declarar en el pedimento los números de serie, parte, marca, modelo o especificaciones técnicas necesarias para identificarlas y distinguirlas de otras similares | D9: Art. 36-A Ley Aduanera | E9: Adjuntar comprobante en caso de contar con mercancías susceptibles de identificación individual | F9: Cliente
A10: 2 | B10: Pendiente | C10: La tenencia, transporte o manejo de mercancías de procedencia extranjera deberá ampararse en todo momento con: (I) documentación aduanera de legal importación, (II) nota de venta expedida por autoridad fiscal o institución autorizada, o (III) CFDI que reúna los requisitos del CFF | D10: Art. 146 Ley Aduanera | E10: Adjuntar documentación comprobatoria conforme a la fracción I, II o III según corresponda para cada activo | F10: Cliente
A11: 3 | B11: Pendiente | C11: Mantener los activos fijos importados temporalmente en los domicilios registrados en el Programa IMMEX | D11: Art. 24 Fracc. VI Decreto IMMEX | E11: Confirmar la legal estancia de los activos en los domicilios autorizados | F11: Cliente
A12: 4 | B12: Pendiente | C12: Llevar el control de inventarios de activo fijo en forma automatizada y permanente conforme al Módulo de Activo Fijo del Anexo 24, que debe incluir: descripción con marca y modelo (maquinaria/equipo); número y fecha de pedimento; clave del pedimento; movimientos de importación, exportación, retorno, transferencia, donación, destrucción y cambios de régimen | D12: Art. 24 Fracc. IX Decreto IMMEX Regla 4.3.1 RGCE Anexo 24 | E12: Revisar que el sistema de inventarios cuente con el Módulo de Activo Fijo con toda la información requerida. Adjuntar reporte del módulo | F12: Asesor
A13: Verificación de plazos de retorno — Activo fijo
A14: 5 | B14: Pendiente | C14: Verificar que los activos fijos importados temporalmente que ya no se utilizan en el proceso productivo hayan sido retornados al extranjero, transferidos o su régimen cambiado, antes del vencimiento del Programa IMMEX | D14: Art. 24 Fracc. V Art. 4 Decreto IMMEX | E14: Cruzar el inventario de activo fijo con los pedimentos de retorno/transferencia para identificar activos sin descargo | F14: Asesor
A15: 6 | B15: Pendiente | C15: Verificar que los activos fijos dados de baja (donación o destrucción) cuenten con los avisos correspondientes transmitidos al SCCCyG | D15: Regla 7.2.1 párr. II fracc. IV Anexo 30 | E15: Adjuntar acuses de transmisión de avisos de donación y destrucción en el SCCCyG | F15: Asesor

Sheet Obligaciones
A2: 3. OBLIGACIONES PERMANENTES — Regla 7.2.1 + Decreto IMMEX
A3: Obligaciones de cumplimiento continuo durante la vigencia del registro
A4: RGCE 2026 (DOF 27/12/2025) · Decreto IMMEX vigente
A6: # | B6: Estatus | C6: Obligación / Requisito / Causal | D6: Referencia normativa | E6: Documento / Evidencia de cumplimiento | F6: Responsable | G6: Fecha de cumplimiento
A7: 3.1 Obligaciones generales — todos los registros (Regla 7.2.1)
A8: 1 | B8: Pendiente | C8: Cumplir permanentemente con los requisitos del rubro otorgado | D8: 7.2.1 fracc. I | F8: Asesor
A9: 2 | B9: Pendiente | C9: Estar permanentemente al corriente en obligaciones fiscales y aduaneras | D9: 7.2.1 fracc. II | F9: Cliente
A10: 3 | B10: Pendiente | C10: Dar aviso de cambio en el documento de legal uso y goce del inmueble (vigencia, partes, domicilio) mediante ficha 62/LA | D10: 7.2.1 fracc. VIII | E10: Adjuntar avisos correspondientes CERTIVA sobre los inmuebles | F10: Cliente
A11: 4 | B11: Pendiente | C11: Presentar aviso previo al menos 1 mes antes de introducir mercancías adicionales a las declaradas, mediante ficha 62/LA | D11: 7.2.1 fracc. X | E11: Adjuntar aviso de fracciones presentados | F11: Cliente
A12: 5 | B12: Pendiente | C12: Permitir en todo momento el acceso de la autoridad aduanera para inspecciones de supervisión de cumplimiento | D12: 7.2.1 fracc. VII | F12: Cliente
A13: 6 | B13: Pendiente | C13: En caso de fusión/escisión: dar aviso ante la AGACE dentro de los 10 días posteriores a la inscripción en el Registro Público de Comercio — ficha 62/LA | D13: 7.2.1 fracc. V | E13: Confirmar que no existe fusión o escisión | F13: Cliente
A14: 3.2 Obligaciones específicas — Modalidad IVA e IEPS (Rubros A, AA y AAA)
A15: 7 | B15: Pendiente | C15: Reportar mensualmente a la AGACE (mes siguiente) modificaciones de socios, accionistas, representante legal, clientes y proveedores extranjeros, y proveedores nacionales | D15: 7.2.1 segundo párrafo fracc. I | E15: Adjuntar aviso en caso de haber modificaciones de socios, accionistas, representante legal, proveedores y clientes | F15: Cliente
A16: 8 | B16: Pendiente | C16: Acreditar continuidad del legal uso y goce del inmueble para los procesos productivos | D16: 7.2.1 segundo párrafo fracc. II | E16: Adjuntar legal uso y estancia del inmueble (contrato de arrendamiento o compraventa) | F16: Cliente
A17: 9 | B17: Pendiente | C17: Estar permanentemente al corriente en el pago de cuotas obrero-patronales ante el IMSS | D17: 7.2.1 segundo párrafo fracc. III | E17: Confirmar con área de Finanzas | F17: Cliente
A18: 10 | B18: Pendiente | C18: Transmitir electrónicamente (Anexo 30 / Portal SAT) informes de descargo: retornos, cambios de régimen, transferencias virtuales, extracciones, regularizaciones, donaciones y destrucciones en el SCCCyG | D18: 7.2.1 segundo párrafo fracc. IV · Anexo 30 | E18: Confirmar que se transmite — estatus 'válido' en SCCCyG | F18: Asesor
A19: 11 | B19: Pendiente | C19: Transmitir inventario de mercancías y/o activo fijo pendiente de retorno en un plazo máximo de 30 días naturales posteriores a la fecha de certificación | D19: 7.2.1 segundo párrafo fracc. IV (inv.) | E19: Confirmar que fue transmitido | F19: Asesor

Sheet Requerimiento
A2: 4. CAUSAS DE REQUERIMIENTO — Regla 7.2.2
A3: Situaciones que activan un requerimiento de la AGACE
A4: RGCE 2026 (DOF 27/12/2025) · Decreto IMMEX vigente
A6: # | B6: Estatus | C6: Obligación / Requisito / Causal | D6: Referencia normativa | E6: Documento / Evidencia de cumplimiento | F6: Responsable | G6: Fecha de cumplimiento
A7: 4.1 Causas generales — todos los registros (Regla 7.2.2)
A8: ℹ️ La AGACE otorga 20 días hábiles para subsanar o desvirtuar. Si no se subsana, se inicia el procedimiento de cancelación. La AGACE tiene 6 meses para emitir resolución.
A9: 1 | B9: Pendiente | C9: La empresa no está al corriente en el cumplimiento de obligaciones fiscales | D9: 7.2.2 fracc. I inciso a) | F9: Asesor
A10: 2 | B10: Pendiente | C10: Incumplimiento de la obligación de retener y enterar el ISR de trabajadores | D10: 7.2.2 fracc. I inciso b) | E10: Adjuntar última declaración de retención de ISR | F10: Cliente
A11: 3 | B11: Pendiente | C11: Ubicarse en los listados del SAT: art. 69 CFF (exc. fracc. VI), art. 69-B cuarto párrafo, o art. 69-B Bis noveno párrafo | D11: 7.2.2 fracc. I inciso c) | E11: Confirmar con Finanzas que ningún proveedor se encuentra en listados 69, 69-B y 69-B Bis | F11: Asesor
A12: 4 | B12: Pendiente | C12: Ubicarse en causales del art. 17-H Bis del CFF (restricción de sellos digitales) | D12: 7.2.2 fracc. I inciso d) | E12: Confirmar con Finanzas | F12: Cliente
A13: 5 | B13: Pendiente | C13: Dejar de cumplir con las obligaciones establecidas en la regla 7.2.1 | D13: 7.2.2 fracc. I inciso e) | F13: Asesor
A14: 6 | B14: Pendiente | C14: No haber realizado el pago de derechos anual o por renovación (art. 40 inciso m) LFD, esquema e5cinco) | D14: 7.2.2 fracc. I inciso f) | E14: Adjuntar pago de derechos y última renovación | F14: Cliente
A15: 7 | B15: Pendiente | C15: Haberse emitido y notificado resolución de emisión de falsos comprobantes fiscales (art. 49 Bis CFF) | D15: 7.2.2 fracc. I inciso g) | E15: Confirmar con Finanzas | F15: Cliente
A16: 4.2 Causas específicas — Rubros A, AA y AAA
A17: 8 | B17: Pendiente | C17: Socios, accionistas, representante legal o administración no al corriente en obligaciones fiscales | D17: 7.2.2 fracc. II inciso a) | E17: Adjuntar última acta de asamblea y opinión positiva de socios/accionistas | F17: Cliente
A18: 9 | B18: Pendiente | C18: Personal insuficiente, no registrado en IMSS, no al corriente en cuotas o sin retención/entero de ISR; en subcontratación, omisión art. 27 fracc. V Ley ISR | D18: 7.2.2 fracc. II inciso b) | F18: Asesor
A19: 10 | B19: Pendiente | C19: Proveedores nacionales de insumos no al corriente en obligaciones fiscales | D19: 7.2.2 fracc. II inciso c) | E19: Adjuntar Excel de aviso presentado en CERTIVA y opiniones positivas de proveedores | F19: Cliente
A20: 11 | B20: Pendiente | C20: Dejar de acreditar el legal uso y goce del inmueble para los procesos productivos | D20: 7.2.2 fracc. II inciso d) | F20: Asesor
A21: 12 | B21: Pendiente | C21: Rubro AA o AAA: determinación y notificación de un crédito fiscal | D21: 7.2.2 fracc. II inciso e) | F21: Cliente
A22: 13 | B22: Pendiente | C22: Resoluciones de improcedencia de devolución de IVA >20% del total autorizado y/o monto negado >$5,000,000 pesos en los últimos 6 meses | D22: 7.2.2 fracc. II inciso f) | E22: Confirmar con Finanzas | F22: Cliente
A23: 14 | B23: Pendiente | C23: No transmisión del informe de inventario existente o inicial, o de informes de descargo conforme al Anexo 30 | D23: 7.2.2 fracc. II inciso g) | E23: Confirmar que fue transmitido | F23: Asesor
A24: 15 | B24: Pendiente | C24: Control de inventarios no conforme al art. 59 fracc. I Ley Aduanera y disposiciones del SAT | D24: 7.2.2 fracc. II inciso h) | F24: Asesor
A25: 16 | B25: Pendiente | C25: Proveedores en listados SAT: art. 49 Bis fracc. X o art. 69-B cuarto párrafo CFF | D25: 7.2.2 fracc. II inciso i) | F25: Asesor

Sheet Cancelacion
A2: 5. CAUSAS DE CANCELACIÓN Y SUSPENSIÓN — Regla 7.2.4
A3: Situaciones que pueden derivar en la cancelación o suspensión del registro CERTIVA
A4: RGCE 2026 (DOF 27/12/2025) · Decreto IMMEX vigente
A6: # | B6: Estatus | C6: Obligación / Requisito / Causal | D6: Referencia normativa | E6: Documento / Evidencia de cumplimiento | F6: Responsable | G6: Fecha de cumplimiento
A7: 5.1 Causales generales — Apartado A (Rubros A, AA, AAA y Socio Comercial)
A8: ℹ️ La AGACE notifica el inicio del procedimiento; el contribuyente tiene 10 días para ofrecer pruebas y alegatos. La resolución debe emitirse en ≤4 meses. Los cancelados no podrán obtener el registro durante 2 años.
A9: 1 | B9: Pendiente | C9: No desvirtuar las inconsistencias que generaron un requerimiento (regla 7.2.2) | D9: 7.2.4 Apt. A, fracc. I | F9: Asesor
A10: 2 | B10: Pendiente | C10: No presentar los avisos establecidos en la regla 7.2.1 | D10: 7.2.4 Apt. A, fracc. II | F10: Asesor
A11: 3 | B11: Pendiente | C11: No acreditar durante la inspección de supervisión que se cuenta con la infraestructura necesaria para las actividades autorizadas | D11: 7.2.4 Apt. A, fracc. III | F11: Cliente
A12: 4 | B12: Pendiente | C12: No llevar el sistema de control de inventarios de forma automatizada | D12: 7.2.4 Apt. A, fracc. IV | F12: Asesor
A13: 5 | B13: Pendiente | C13: Presentar o declarar documentación o información falsa, alterada o con datos falsos en cualquier trámite o en operaciones de comercio exterior | D13: 7.2.4 Apt. A, fracc. V | F13: Cliente
A14: 6 | B14: Pendiente | C14: El SAT interponga querella, denuncia penal o declaratoria de perjuicio contra socios, accionistas, representante legal o integrantes de la administración | D14: 7.2.4 Apt. A, fracc. VI | F14: Cliente
A15: 7 | B15: Pendiente | C15: Contribuyente no localizado en domicilio fiscal o establecimientos no localizados/inexistentes | D15: 7.2.4 Apt. A, fracc. VII | E15: Adjuntar capturas SAT mostrando domicilios localizados | F15: Cliente
A16: 8 | B16: Pendiente | C16: Importar temporalmente mercancías del Anexo II del Decreto IMMEX sin autorización, o importar fracciones que no corresponden al proceso productivo | D16: 7.2.4 Apt. A, fracc. VIII | F16: Asesor
A17: 9 | B17: Pendiente | C17: Socios/accionistas, representante legal o administración vinculados con empresa a quien se le canceló el registro (fracc. V, VI, VII Apt. A o II, III Apt. B) | D17: 7.2.4 Apt. A, fracc. IX | E17: Confirmar que los socios no están vinculados a lo establecido en este artículo | F17: Cliente
A18: 10 | B18: Pendiente | C18: Nombre o domicilio del proveedor/productor, destinatario o comprador en pedimentos, CFDI o información proporcionada sean falsos, inexistentes o no localizados | D18: 7.2.4 Apt. A, fracc. X | E18: Adjuntar comprobantes | F18: Asesor
A19: 5.2 Causales específicas IVA e IEPS — Apartado B (Rubros A, AA, AAA)
A20: 11 | B20: Pendiente | C20: Cancelación definitiva de la autorización, permiso o régimen aduanero bajo el cual se otorgó el registro (ej. cancelación definitiva del Programa IMMEX) | D20: 7.2.4 Apt. B, fracc. I | F20: Cliente
A21: 12 | B21: Pendiente | C21: Empresas IMMEX: mercancías importadas temporalmente no retornadas, transferidas ni destinadas a otro régimen dentro del plazo autorizado | D21: 7.2.4 Apt. B, fracc. II | F21: Asesor
A22: 13 | B22: Pendiente | C22: Las autoridades aduaneras detectan que las mercancías importadas temporalmente no se encuentran en los domicilios autorizados | D22: 7.2.4 Apt. B, fracc. III | F22: Cliente
A23: 14 | B23: Pendiente | C23: No acreditar la legal estancia de mercancías de comercio exterior por más de $100,000 pesos y no cubrir el crédito fiscal determinado y notificado por el SAT | D23: 7.2.4 Apt. B, fracc. IV | F23: Cliente
A24: 15 | B24: Pendiente | C24: Suspensión definitiva confirmada en el Padrón de Importadores o padrones específicos/sectoriales | D24: 7.2.4 Apt. B, fracc. V | F24: Cliente
A25: 16 | B25: Pendiente | C25: La AGACE constata (inspección o facultades de comprobación) que no cuenta con infraestructura para operar el Programa IMMEX/RFE/depósito fiscal; incumple proceso productivo o no tiene la inversión declarada | D25: 7.2.4 Apt. B, fracc. VI | F25: Asesor
A26: 17 | B26: Pendiente | C26: No haber retornado mercancías importadas temporalmente conforme a los porcentajes de la regla 7.1.2 (Apartados A fracc. III y B) | D26: 7.2.4 Apt. B, fracc. VII | F26: Asesor
A27: 5.3 Causales de suspensión del registro
A28: 18 | B28: Pendiente | C28: Suspensión del Programa IMMEX por parte de la SE (el registro se suspende mientras dure; si se cancela el IMMEX, se inicia cancelación del registro) | D28: 7.2.4 Suspensión, fracc. I | F28: Cliente
A29: 19 | B29: Pendiente | C29: Clave en el RFC suspendida por la autoridad competente (hasta que la autoridad resuelva la situación) | D29: 7.2.4 Suspensión, fracc. II | F29: Cliente
A30: 20 | B30: Pendiente | C30: Impedir el acceso a la AGACE para llevar a cabo la supervisión de cumplimiento, sin solicitar nueva fecha dentro de los 15 días siguientes | D30: 7.2.4 Suspensión, fracc. III | F30: Cliente
